mdna/__init__.py
mdna/analysis.py
mdna/build.py
mdna/generators.py
mdna/geometry.py
mdna/minimizer.py
mdna/modify.py
mdna/nucleic.py
mdna/spline.py
mdna/utils.py
mdna/PMCpy/.git
mdna/PMCpy/.gitignore
mdna/PMCpy/.gitmodules
mdna/PMCpy/LICENSE
mdna/PMCpy/README.md
mdna/PMCpy/setup.py
mdna/PMCpy/test_run.py
mdna/PMCpy/pmcpy/__init__.py
mdna/PMCpy/pmcpy/aux.py
mdna/PMCpy/pmcpy/chain.py
mdna/PMCpy/pmcpy/pmc.py
mdna/PMCpy/pmcpy/run_free.py
mdna/PMCpy/pmcpy/run_tweezer.py
mdna/PMCpy/pmcpy/test_nonlocal.py
mdna/PMCpy/pmcpy/BPStep/BPS_LRBP.py
mdna/PMCpy/pmcpy/BPStep/BPS_RBP.py
mdna/PMCpy/pmcpy/BPStep/BPStep.py
mdna/PMCpy/pmcpy/BPStep/__init__.py
mdna/PMCpy/pmcpy/BPStep/RBPStiff/.git
mdna/PMCpy/pmcpy/BPStep/RBPStiff/.gitignore
mdna/PMCpy/pmcpy/BPStep/RBPStiff/.gitmodules
mdna/PMCpy/pmcpy/BPStep/RBPStiff/LICENSE
mdna/PMCpy/pmcpy/BPStep/RBPStiff/README.md
mdna/PMCpy/pmcpy/BPStep/RBPStiff/__init__.py
mdna/PMCpy/pmcpy/BPStep/RBPStiff/groundstate.py
mdna/PMCpy/pmcpy/BPStep/RBPStiff/read_params.py
mdna/PMCpy/pmcpy/BPStep/RBPStiff/setup.py
mdna/PMCpy/pmcpy/BPStep/RBPStiff/Parametrization/Crystallography/Equilibrium-C-AA.txt
mdna/PMCpy/pmcpy/BPStep/RBPStiff/Parametrization/Crystallography/Equilibrium-C-AC.txt
mdna/PMCpy/pmcpy/BPStep/RBPStiff/Parametrization/Crystallography/Equilibrium-C-AG.txt
mdna/PMCpy/pmcpy/BPStep/RBPStiff/Parametrization/Crystallography/Equilibrium-C-AT.txt
mdna/PMCpy/pmcpy/BPStep/RBPStiff/Parametrization/Crystallography/Equilibrium-C-Ave.txt
mdna/PMCpy/pmcpy/BPStep/RBPStiff/Parametrization/Crystallography/Equilibrium-C-CA.txt
mdna/PMCpy/pmcpy/BPStep/RBPStiff/Parametrization/Crystallography/Equilibrium-C-CC.txt
mdna/PMCpy/pmcpy/BPStep/RBPStiff/Parametrization/Crystallography/Equilibrium-C-CG.txt
mdna/PMCpy/pmcpy/BPStep/RBPStiff/Parametrization/Crystallography/Equilibrium-C-CT.txt
mdna/PMCpy/pmcpy/BPStep/RBPStiff/Parametrization/Crystallography/Equilibrium-C-GA.txt
mdna/PMCpy/pmcpy/BPStep/RBPStiff/Parametrization/Crystallography/Equilibrium-C-GC.txt
mdna-0.0.2.dist-info/METADATA
mdna-0.0.2.dist-info/WHEEL
mdna-0.0.2.dist-info/licenses/LICENSE
mdna-0.0.2.dist-info/RECORD
