Metadata-Version: 2.4
Name: mdna
Version: 0.0.2
Summary: Software module for DNA structure analysis and generation
Project-URL: Homepage, https://github.com/heezch/mdna
Author-email: Thor van Heesch <t.vanheesch@uva.nl>
License: MIT License
License-File: LICENSE
Keywords: Molecular Dynamics,Molecular Toolkit,Structuer Generation Tool,Structure Analysis
Classifier: Development Status :: 3 - Alpha
Classifier: License :: OSI Approved :: MIT License
Classifier: Operating System :: OS Independent
Classifier: Programming Language :: Python :: 3
Requires-Python: >=3.10
Requires-Dist: biopython
Requires-Dist: matplotlib
Requires-Dist: mdtraj
Requires-Dist: numba
Requires-Dist: numpy
Requires-Dist: scipy
